[{"cost":626.79,"chargeLevel":13},
{"cost":804.12,"chargeLevel":55},
{"cost":554.51,"chargeLevel":42},
{"cost":362.99,"chargeLevel":78},
{"cost":893.89,"chargeLevel":13},
{"cost":821.43,"chargeLevel":66},
{"cost":299.93,"chargeLevel":34},
{"cost":126.27,"chargeLevel":92},
{"cost":548.08,"chargeLevel":36},
{"cost":820.18,"chargeLevel":93},
{"cost":646.27,"chargeLevel":71},
{"cost":945.71,"chargeLevel":71},
{"cost":396.47,"chargeLevel":91},
{"cost":950.13,"chargeLevel":17},
{"cost":109.06,"chargeLevel":14},
{"cost":418.84,"chargeLevel":63},
{"cost":420.3,"chargeLevel":89},
{"cost":695.89,"chargeLevel":54},
{"cost":660.19,"chargeLevel":23},
{"cost":367.22,"chargeLevel":69},
{"cost":455.87,"chargeLevel":20},
{"cost":933.22,"chargeLevel":40},
{"cost":403.25,"chargeLevel":93},
{"cost":108.75,"chargeLevel":12},
{"cost":884.57,"chargeLevel":4},
{"cost":115.19,"chargeLevel":71},
{"cost":751.72,"chargeLevel":9},
{"cost":452.61,"chargeLevel":15},
{"cost":460.41,"chargeLevel":5},
{"cost":195.48,"chargeLevel":45},
{"cost":734.25,"chargeLevel":62},
{"cost":626.61,"chargeLevel":28},
{"cost":703.25,"chargeLevel":41},
{"cost":163.68,"chargeLevel":88},
{"cost":980.04,"chargeLevel":79},
{"cost":941.47,"chargeLevel":82},
{"cost":926.42,"chargeLevel":11},
{"cost":829.61,"chargeLevel":93},
{"cost":48.86,"chargeLevel":44},
{"cost":13.02,"chargeLevel":80},
{"cost":812.58,"chargeLevel":53},
{"cost":533.53,"chargeLevel":98},
{"cost":624.13,"chargeLevel":86},
{"cost":520.98,"chargeLevel":70},
{"cost":98.13,"chargeLevel":42},
{"cost":92.88,"chargeLevel":98},
{"cost":905.17,"chargeLevel":66},
{"cost":299.99,"chargeLevel":2},
{"cost":146.35,"chargeLevel":64},
{"cost":609.16,"chargeLevel":95},
{"cost":167.52,"chargeLevel":29},
{"cost":316.78,"chargeLevel":46},
{"cost":997.38,"chargeLevel":27},
{"cost":769.13,"chargeLevel":90},
{"cost":69.77,"chargeLevel":61},
{"cost":770.62,"chargeLevel":64},
{"cost":975.44,"chargeLevel":87},
{"cost":393.27,"chargeLevel":17},
{"cost":827.72,"chargeLevel":96},
{"cost":845.54,"chargeLevel":78},
{"cost":356.45,"chargeLevel":75},
{"cost":506.42,"chargeLevel":25},
{"cost":684.04,"chargeLevel":26},
{"cost":232.62,"chargeLevel":45},
{"cost":892.93,"chargeLevel":82},
{"cost":646.23,"chargeLevel":71},
{"cost":195.88,"chargeLevel":18},
{"cost":257.6,"chargeLevel":57},
{"cost":315.44,"chargeLevel":84},
{"cost":752.61,"chargeLevel":60},
{"cost":736.08,"chargeLevel":41},
{"cost":506.64,"chargeLevel":89},
{"cost":230.39,"chargeLevel":58},
{"cost":938.55,"chargeLevel":42},
{"cost":126.09,"chargeLevel":90},
{"cost":196.93,"chargeLevel":59},
{"cost":872.48,"chargeLevel":97},
{"cost":887.41,"chargeLevel":96},
{"cost":219.47,"chargeLevel":75},
{"cost":783.31,"chargeLevel":1},
{"cost":608.74,"chargeLevel":86},
{"cost":209.31,"chargeLevel":46},
{"cost":29.36,"chargeLevel":35},
{"cost":824.46,"chargeLevel":38},
{"cost":962.15,"chargeLevel":92},
{"cost":910.81,"chargeLevel":69},
{"cost":718.09,"chargeLevel":29},
{"cost":964.13,"chargeLevel":96},
{"cost":588.49,"chargeLevel":28},
{"cost":624.35,"chargeLevel":20},
{"cost":391.38,"chargeLevel":58},
{"cost":573.95,"chargeLevel":100},
{"cost":174.43,"chargeLevel":30},
{"cost":151.36,"chargeLevel":31},
{"cost":613.02,"chargeLevel":52},
{"cost":247.23,"chargeLevel":48},
{"cost":151.44,"chargeLevel":99},
{"cost":548.89,"chargeLevel":46},
{"cost":927.82,"chargeLevel":7},
{"cost":243.35,"chargeLevel":22},
{"cost":819.54,"chargeLevel":42},
{"cost":109.19,"chargeLevel":54},
{"cost":262.84,"chargeLevel":15},
{"cost":380.82,"chargeLevel":19},
{"cost":996.46,"chargeLevel":83},
{"cost":499.02,"chargeLevel":63},
{"cost":653.0,"chargeLevel":89},
{"cost":372.1,"chargeLevel":49},
{"cost":539.81,"chargeLevel":43},
{"cost":997.77,"chargeLevel":34},
{"cost":185.42,"chargeLevel":12},
{"cost":919.47,"chargeLevel":97},
{"cost":690.28,"chargeLevel":20},
{"cost":534.45,"chargeLevel":25},
{"cost":355.29,"chargeLevel":35},
{"cost":994.77,"chargeLevel":87},
{"cost":15.82,"chargeLevel":25},
{"cost":738.41,"chargeLevel":89},
{"cost":263.44,"chargeLevel":38},
{"cost":712.99,"chargeLevel":3},
{"cost":307.26,"chargeLevel":7},
{"cost":293.1,"chargeLevel":62},
{"cost":621.72,"chargeLevel":39},
{"cost":604.12,"chargeLevel":53},
{"cost":472.93,"chargeLevel":73},
{"cost":856.31,"chargeLevel":54},
{"cost":760.16,"chargeLevel":6},
{"cost":375.36,"chargeLevel":33},
{"cost":881.73,"chargeLevel":93},
{"cost":891.28,"chargeLevel":90},
{"cost":80.93,"chargeLevel":77},
{"cost":596.95,"chargeLevel":3},
{"cost":914.16,"chargeLevel":48},
{"cost":199.58,"chargeLevel":22},
{"cost":25.98,"chargeLevel":32},
{"cost":905.27,"chargeLevel":1},
{"cost":478.54,"chargeLevel":21},
{"cost":117.93,"chargeLevel":65},
{"cost":560.66,"chargeLevel":19},
{"cost":596.48,"chargeLevel":87},
{"cost":116.1,"chargeLevel":93},
{"cost":700.48,"chargeLevel":59},
{"cost":706.64,"chargeLevel":79},
{"cost":791.41,"chargeLevel":13},
{"cost":828.39,"chargeLevel":4},
{"cost":354.95,"chargeLevel":52},
{"cost":885.02,"chargeLevel":42},
{"cost":51.43,"chargeLevel":43},
{"cost":4.11,"chargeLevel":50},
{"cost":333.14,"chargeLevel":26},
{"cost":856.85,"chargeLevel":47},
{"cost":624.59,"chargeLevel":28},
{"cost":382.61,"chargeLevel":57},
{"cost":634.39,"chargeLevel":98},
{"cost":577.19,"chargeLevel":90},
{"cost":822.71,"chargeLevel":74},
{"cost":153.19,"chargeLevel":72},
{"cost":827.23,"chargeLevel":52},
{"cost":281.03,"chargeLevel":40},
{"cost":543.43,"chargeLevel":7},
{"cost":747.96,"chargeLevel":79},
{"cost":720.72,"chargeLevel":50},
{"cost":287.12,"chargeLevel":30},
{"cost":613.78,"chargeLevel":61},
{"cost":565.4,"chargeLevel":25},
{"cost":686.84,"chargeLevel":8},
{"cost":732.59,"chargeLevel":11},
{"cost":742.44,"chargeLevel":4},
{"cost":840.48,"chargeLevel":97},
{"cost":357.14,"chargeLevel":7},
{"cost":280.97,"chargeLevel":69},
{"cost":404.83,"chargeLevel":100},
{"cost":624.41,"chargeLevel":100},
{"cost":677.4,"chargeLevel":77},
{"cost":436.04,"chargeLevel":66},
{"cost":224.3,"chargeLevel":27},
{"cost":466.98,"chargeLevel":99},
{"cost":863.96,"chargeLevel":49},
{"cost":846.78,"chargeLevel":5},
{"cost":212.31,"chargeLevel":90},
{"cost":504.6,"chargeLevel":26},
{"cost":106.08,"chargeLevel":8},
{"cost":995.52,"chargeLevel":79},
{"cost":396.92,"chargeLevel":74},
{"cost":10.69,"chargeLevel":44},
{"cost":164.23,"chargeLevel":9},
{"cost":51.15,"chargeLevel":78},
{"cost":239.83,"chargeLevel":39},
{"cost":554.64,"chargeLevel":73},
{"cost":399.93,"chargeLevel":2},
{"cost":908.58,"chargeLevel":32},
{"cost":135.39,"chargeLevel":69},
{"cost":492.48,"chargeLevel":28},
{"cost":867.51,"chargeLevel":94},
{"cost":861.12,"chargeLevel":19},
{"cost":693.67,"chargeLevel":88},
{"cost":392.07,"chargeLevel":40},
{"cost":325.32,"chargeLevel":98},
{"cost":613.69,"chargeLevel":24},
{"cost":745.34,"chargeLevel":53},
{"cost":38.04,"chargeLevel":74},
{"cost":588.68,"chargeLevel":96},
{"cost":910.09,"chargeLevel":96},
{"cost":226.67,"chargeLevel":96},
{"cost":292.62,"chargeLevel":85},
{"cost":413.25,"chargeLevel":96},
{"cost":747.36,"chargeLevel":45},
{"cost":970.9,"chargeLevel":57},
{"cost":906.94,"chargeLevel":51},
{"cost":395.68,"chargeLevel":22},
{"cost":840.5,"chargeLevel":6},
{"cost":333.69,"chargeLevel":81},
{"cost":677.49,"chargeLevel":55},
{"cost":797.8,"chargeLevel":44},
{"cost":889.15,"chargeLevel":46},
{"cost":863.91,"chargeLevel":63},
{"cost":23.52,"chargeLevel":10},
{"cost":570.2,"chargeLevel":92},
{"cost":885.09,"chargeLevel":94},
{"cost":409.87,"chargeLevel":81},
{"cost":665.4,"chargeLevel":3},
{"cost":604.32,"chargeLevel":97},
{"cost":385.91,"chargeLevel":69},
{"cost":545.57,"chargeLevel":48},
{"cost":677.81,"chargeLevel":55},
{"cost":400.42,"chargeLevel":65},
{"cost":840.55,"chargeLevel":64},
{"cost":564.94,"chargeLevel":72},
{"cost":752.94,"chargeLevel":65},
{"cost":876.76,"chargeLevel":96},
{"cost":863.78,"chargeLevel":78},
{"cost":782.43,"chargeLevel":39},
{"cost":8.33,"chargeLevel":12},
{"cost":772.68,"chargeLevel":38},
{"cost":553.79,"chargeLevel":43},
{"cost":386.4,"chargeLevel":96},
{"cost":762.77,"chargeLevel":65},
{"cost":311.84,"chargeLevel":79},
{"cost":909.19,"chargeLevel":41},
{"cost":15.99,"chargeLevel":30},
{"cost":804.5,"chargeLevel":79},
{"cost":629.25,"chargeLevel":81},
{"cost":997.27,"chargeLevel":36},
{"cost":825.31,"chargeLevel":67},
{"cost":80.83,"chargeLevel":72},
{"cost":245.08,"chargeLevel":14},
{"cost":600.47,"chargeLevel":29},
{"cost":129.36,"chargeLevel":78},
{"cost":599.97,"chargeLevel":96},
{"cost":40.86,"chargeLevel":8},
{"cost":570.69,"chargeLevel":86},
{"cost":928.33,"chargeLevel":16},
{"cost":361.21,"chargeLevel":30},
{"cost":710.26,"chargeLevel":75},
{"cost":866.31,"chargeLevel":72},
{"cost":16.39,"chargeLevel":83},
{"cost":792.29,"chargeLevel":30},
{"cost":308.88,"chargeLevel":35},
{"cost":995.02,"chargeLevel":36},
{"cost":14.27,"chargeLevel":55},
{"cost":32.34,"chargeLevel":14},
{"cost":325.22,"chargeLevel":2},
{"cost":682.9,"chargeLevel":56},
{"cost":161.26,"chargeLevel":81},
{"cost":110.96,"chargeLevel":81},
{"cost":735.54,"chargeLevel":84},
{"cost":326.35,"chargeLevel":41},
{"cost":50.77,"chargeLevel":98},
{"cost":48.88,"chargeLevel":77},
{"cost":876.31,"chargeLevel":53},
{"cost":260.66,"chargeLevel":79},
{"cost":569.8,"chargeLevel":90},
{"cost":328.63,"chargeLevel":18},
{"cost":804.15,"chargeLevel":96},
{"cost":389.9,"chargeLevel":10},
{"cost":650.36,"chargeLevel":70},
{"cost":92.5,"chargeLevel":65},
{"cost":975.73,"chargeLevel":100},
{"cost":652.53,"chargeLevel":49},
{"cost":966.38,"chargeLevel":9},
{"cost":438.17,"chargeLevel":78},
{"cost":776.92,"chargeLevel":86},
{"cost":34.88,"chargeLevel":60},
{"cost":585.98,"chargeLevel":73},
{"cost":613.18,"chargeLevel":84},
{"cost":857.36,"chargeLevel":72},
{"cost":877.84,"chargeLevel":17},
{"cost":244.77,"chargeLevel":65},
{"cost":88.77,"chargeLevel":1},
{"cost":404.76,"chargeLevel":100},
{"cost":716.66,"chargeLevel":27},
{"cost":401.95,"chargeLevel":32},
{"cost":351.35,"chargeLevel":87},
{"cost":97.84,"chargeLevel":81},
{"cost":290.66,"chargeLevel":76},
{"cost":617.62,"chargeLevel":77},
{"cost":978.11,"chargeLevel":79},
{"cost":262.35,"chargeLevel":7},
{"cost":100.18,"chargeLevel":7},
{"cost":302.26,"chargeLevel":94},
{"cost":122.9,"chargeLevel":36},
{"cost":363.5,"chargeLevel":71},
{"cost":179.82,"chargeLevel":6},
{"cost":178.02,"chargeLevel":34},
{"cost":575.75,"chargeLevel":57},
{"cost":272.95,"chargeLevel":19},
{"cost":349.88,"chargeLevel":87},
{"cost":596.11,"chargeLevel":1},
{"cost":236.35,"chargeLevel":15},
{"cost":306.32,"chargeLevel":46},
{"cost":650.11,"chargeLevel":16},
{"cost":947.65,"chargeLevel":53},
{"cost":234.83,"chargeLevel":57},
{"cost":506.82,"chargeLevel":41},
{"cost":464.69,"chargeLevel":29},
{"cost":500.92,"chargeLevel":55},
{"cost":214.17,"chargeLevel":57},
{"cost":465.42,"chargeLevel":39},
{"cost":196.48,"chargeLevel":75},
{"cost":75.34,"chargeLevel":70},
{"cost":513.48,"chargeLevel":69},
{"cost":17.84,"chargeLevel":1},
{"cost":929.03,"chargeLevel":66},
{"cost":172.68,"chargeLevel":56},
{"cost":891.36,"chargeLevel":17},
{"cost":891.96,"chargeLevel":32},
{"cost":763.99,"chargeLevel":66},
{"cost":404.47,"chargeLevel":29},
{"cost":940.91,"chargeLevel":32},
{"cost":479.01,"chargeLevel":99},
{"cost":389.88,"chargeLevel":37},
{"cost":206.1,"chargeLevel":79},
{"cost":466.46,"chargeLevel":45},
{"cost":187.54,"chargeLevel":70},
{"cost":654.57,"chargeLevel":67},
{"cost":886.69,"chargeLevel":23},
{"cost":758.16,"chargeLevel":66},
{"cost":145.07,"chargeLevel":74},
{"cost":839.47,"chargeLevel":89},
{"cost":711.96,"chargeLevel":5},
{"cost":629.05,"chargeLevel":53},
{"cost":676.9,"chargeLevel":85},
{"cost":13.14,"chargeLevel":49},
{"cost":757.9,"chargeLevel":31},
{"cost":864.96,"chargeLevel":52},
{"cost":850.46,"chargeLevel":72},
{"cost":845.7,"chargeLevel":18},
{"cost":494.72,"chargeLevel":54},
{"cost":614.76,"chargeLevel":25},
{"cost":69.46,"chargeLevel":89},
{"cost":296.47,"chargeLevel":51},
{"cost":614.72,"chargeLevel":30},
{"cost":520.98,"chargeLevel":95},
{"cost":599.26,"chargeLevel":57},
{"cost":592.44,"chargeLevel":3},
{"cost":979.37,"chargeLevel":7},
{"cost":421.74,"chargeLevel":45},
{"cost":828.04,"chargeLevel":8},
{"cost":498.74,"chargeLevel":93},
{"cost":511.49,"chargeLevel":66},
{"cost":9.96,"chargeLevel":56},
{"cost":182.52,"chargeLevel":42},
{"cost":887.32,"chargeLevel":8},
{"cost":452.04,"chargeLevel":51},
{"cost":842.24,"chargeLevel":59},
{"cost":24.35,"chargeLevel":99},
{"cost":258.85,"chargeLevel":7},
{"cost":266.85,"chargeLevel":54},
{"cost":107.86,"chargeLevel":15},
{"cost":898.19,"chargeLevel":99},
{"cost":986.77,"chargeLevel":56},
{"cost":405.74,"chargeLevel":17},
{"cost":85.34,"chargeLevel":79},
{"cost":219.05,"chargeLevel":18},
{"cost":188.41,"chargeLevel":66},
{"cost":172.57,"chargeLevel":57},
{"cost":118.38,"chargeLevel":3},
{"cost":898.15,"chargeLevel":41},
{"cost":256.28,"chargeLevel":100},
{"cost":551.33,"chargeLevel":83},
{"cost":531.99,"chargeLevel":67},
{"cost":801.73,"chargeLevel":83},
{"cost":580.04,"chargeLevel":87},
{"cost":121.2,"chargeLevel":91},
{"cost":926.15,"chargeLevel":72},
{"cost":395.83,"chargeLevel":88},
{"cost":887.59,"chargeLevel":80},
{"cost":275.73,"chargeLevel":30},
{"cost":689.77,"chargeLevel":68},
{"cost":423.51,"chargeLevel":29},
{"cost":435.65,"chargeLevel":86},
{"cost":562.11,"chargeLevel":24},
{"cost":239.48,"chargeLevel":46},
{"cost":258.54,"chargeLevel":12},
{"cost":126.19,"chargeLevel":99},
{"cost":416.38,"chargeLevel":20},
{"cost":420.59,"chargeLevel":36},
{"cost":888.97,"chargeLevel":86},
{"cost":724.12,"chargeLevel":99},
{"cost":937.09,"chargeLevel":63},
{"cost":628.31,"chargeLevel":42},
{"cost":684.77,"chargeLevel":16},
{"cost":76.7,"chargeLevel":5},
{"cost":751.03,"chargeLevel":27},
{"cost":842.65,"chargeLevel":31},
{"cost":235.91,"chargeLevel":11},
{"cost":396.88,"chargeLevel":39},
{"cost":66.72,"chargeLevel":12},
{"cost":856.05,"chargeLevel":99},
{"cost":837.1,"chargeLevel":94},
{"cost":544.78,"chargeLevel":6},
{"cost":779.16,"chargeLevel":86},
{"cost":424.85,"chargeLevel":19},
{"cost":547.05,"chargeLevel":59},
{"cost":222.61,"chargeLevel":92},
{"cost":415.81,"chargeLevel":3},
{"cost":893.0,"chargeLevel":36},
{"cost":423.01,"chargeLevel":4},
{"cost":78.91,"chargeLevel":6},
{"cost":792.99,"chargeLevel":53},
{"cost":541.35,"chargeLevel":72},
{"cost":81.65,"chargeLevel":94},
{"cost":763.1,"chargeLevel":1},
{"cost":797.2,"chargeLevel":32},
{"cost":604.65,"chargeLevel":34},
{"cost":37.43,"chargeLevel":42},
{"cost":397.29,"chargeLevel":75},
{"cost":971.79,"chargeLevel":38},
{"cost":887.64,"chargeLevel":21},
{"cost":258.32,"chargeLevel":56},
{"cost":442.87,"chargeLevel":43},
{"cost":597.48,"chargeLevel":37},
{"cost":572.65,"chargeLevel":46},
{"cost":50.92,"chargeLevel":30},
{"cost":855.26,"chargeLevel":59},
{"cost":182.97,"chargeLevel":24},
{"cost":956.39,"chargeLevel":49},
{"cost":518.53,"chargeLevel":67},
{"cost":781.33,"chargeLevel":97},
{"cost":936.27,"chargeLevel":22},
{"cost":677.99,"chargeLevel":50},
{"cost":594.56,"chargeLevel":21},
{"cost":456.3,"chargeLevel":96},
{"cost":447.7,"chargeLevel":71},
{"cost":275.17,"chargeLevel":11},
{"cost":390.74,"chargeLevel":61},
{"cost":59.83,"chargeLevel":31},
{"cost":350.24,"chargeLevel":54},
{"cost":85.37,"chargeLevel":62},
{"cost":171.08,"chargeLevel":94},
{"cost":367.0,"chargeLevel":19},
{"cost":487.77,"chargeLevel":78},
{"cost":116.83,"chargeLevel":31},
{"cost":719.44,"chargeLevel":10},
{"cost":171.73,"chargeLevel":10},
{"cost":276.64,"chargeLevel":38},
{"cost":618.94,"chargeLevel":72},
{"cost":96.45,"chargeLevel":32},
{"cost":940.52,"chargeLevel":15},
{"cost":655.93,"chargeLevel":30},
{"cost":849.09,"chargeLevel":90},
{"cost":992.7,"chargeLevel":54},
{"cost":423.41,"chargeLevel":48},
{"cost":275.8,"chargeLevel":52},
{"cost":203.86,"chargeLevel":42},
{"cost":243.7,"chargeLevel":1},
{"cost":684.13,"chargeLevel":73},
{"cost":950.83,"chargeLevel":1},
{"cost":80.35,"chargeLevel":84},
{"cost":992.4,"chargeLevel":63},
{"cost":96.68,"chargeLevel":61},
{"cost":715.56,"chargeLevel":69},
{"cost":925.06,"chargeLevel":29},
{"cost":648.21,"chargeLevel":47},
{"cost":838.41,"chargeLevel":26},
{"cost":773.42,"chargeLevel":35},
{"cost":835.31,"chargeLevel":39},
{"cost":734.88,"chargeLevel":92},
{"cost":999.77,"chargeLevel":50},
{"cost":951.35,"chargeLevel":76},
{"cost":547.25,"chargeLevel":58},
{"cost":970.32,"chargeLevel":60},
{"cost":897.09,"chargeLevel":23},
{"cost":86.62,"chargeLevel":44},
{"cost":341.67,"chargeLevel":57},
{"cost":47.6,"chargeLevel":41},
{"cost":582.24,"chargeLevel":50},
{"cost":92.3,"chargeLevel":33},
{"cost":227.72,"chargeLevel":74},
{"cost":119.39,"chargeLevel":57},
{"cost":819.58,"chargeLevel":34},
{"cost":554.1,"chargeLevel":82},
{"cost":541.33,"chargeLevel":83},
{"cost":368.09,"chargeLevel":55},
{"cost":188.93,"chargeLevel":79},
{"cost":219.78,"chargeLevel":79},
{"cost":382.32,"chargeLevel":76},
{"cost":30.14,"chargeLevel":58},
{"cost":888.87,"chargeLevel":61},
{"cost":675.48,"chargeLevel":66},
{"cost":356.82,"chargeLevel":60},
{"cost":36.17,"chargeLevel":23},
{"cost":742.96,"chargeLevel":88},
{"cost":196.94,"chargeLevel":80},
{"cost":645.28,"chargeLevel":89},
{"cost":897.03,"chargeLevel":10},
{"cost":892.65,"chargeLevel":89},
{"cost":856.3,"chargeLevel":39},
{"cost":721.86,"chargeLevel":37},
{"cost":543.62,"chargeLevel":50},
{"cost":21.8,"chargeLevel":97},
{"cost":189.29,"chargeLevel":36},
{"cost":929.86,"chargeLevel":11},
{"cost":217.57,"chargeLevel":3},
{"cost":231.23,"chargeLevel":46},
{"cost":920.37,"chargeLevel":43},
{"cost":55.22,"chargeLevel":16},
{"cost":648.89,"chargeLevel":76},
{"cost":481.43,"chargeLevel":60},
{"cost":995.84,"chargeLevel":40},
{"cost":484.72,"chargeLevel":14},
{"cost":317.29,"chargeLevel":100},
{"cost":369.69,"chargeLevel":80},
{"cost":392.51,"chargeLevel":48},
{"cost":921.5,"chargeLevel":54},
{"cost":177.31,"chargeLevel":14},
{"cost":70.16,"chargeLevel":55},
{"cost":530.57,"chargeLevel":78},
{"cost":333.36,"chargeLevel":84},
{"cost":986.39,"chargeLevel":65},
{"cost":621.8,"chargeLevel":13},
{"cost":812.05,"chargeLevel":4},
{"cost":92.86,"chargeLevel":32},
{"cost":828.78,"chargeLevel":86},
{"cost":427.41,"chargeLevel":41},
{"cost":40.82,"chargeLevel":37},
{"cost":915.72,"chargeLevel":2},
{"cost":368.71,"chargeLevel":7},
{"cost":486.92,"chargeLevel":12},
{"cost":864.36,"chargeLevel":27},
{"cost":553.3,"chargeLevel":22},
{"cost":23.51,"chargeLevel":21},
{"cost":97.19,"chargeLevel":69},
{"cost":787.7,"chargeLevel":33},
{"cost":68.64,"chargeLevel":36},
{"cost":613.42,"chargeLevel":77},
{"cost":896.76,"chargeLevel":10},
{"cost":397.98,"chargeLevel":6},
{"cost":537.42,"chargeLevel":2},
{"cost":933.88,"chargeLevel":90},
{"cost":584.95,"chargeLevel":70},
{"cost":164.39,"chargeLevel":52},
{"cost":5.24,"chargeLevel":98},
{"cost":525.86,"chargeLevel":12},
{"cost":956.8,"chargeLevel":63},
{"cost":125.23,"chargeLevel":92},
{"cost":597.0,"chargeLevel":12},
{"cost":732.2,"chargeLevel":45},
{"cost":104.24,"chargeLevel":21},
{"cost":224.81,"chargeLevel":5},
{"cost":148.09,"chargeLevel":49},
{"cost":256.74,"chargeLevel":37},
{"cost":666.03,"chargeLevel":78},
{"cost":311.13,"chargeLevel":28},
{"cost":341.83,"chargeLevel":5},
{"cost":144.21,"chargeLevel":83},
{"cost":610.51,"chargeLevel":7},
{"cost":426.13,"chargeLevel":74},
{"cost":522.16,"chargeLevel":75},
{"cost":89.02,"chargeLevel":41},
{"cost":163.02,"chargeLevel":1},
{"cost":774.94,"chargeLevel":20},
{"cost":777.73,"chargeLevel":95},
{"cost":881.5,"chargeLevel":52},
{"cost":111.44,"chargeLevel":3},
{"cost":414.44,"chargeLevel":33},
{"cost":385.34,"chargeLevel":63},
{"cost":221.33,"chargeLevel":74},
{"cost":479.13,"chargeLevel":6},
{"cost":9.6,"chargeLevel":44},
{"cost":500.47,"chargeLevel":81},
{"cost":832.12,"chargeLevel":44},
{"cost":416.59,"chargeLevel":69},
{"cost":271.76,"chargeLevel":29},
{"cost":122.04,"chargeLevel":48},
{"cost":545.5,"chargeLevel":22},
{"cost":904.79,"chargeLevel":49},
{"cost":149.77,"chargeLevel":27},
{"cost":577.58,"chargeLevel":34},
{"cost":781.5,"chargeLevel":95},
{"cost":594.44,"chargeLevel":93},
{"cost":282.54,"chargeLevel":56},
{"cost":466.82,"chargeLevel":55},
{"cost":289.25,"chargeLevel":1},
{"cost":636.5,"chargeLevel":35},
{"cost":158.18,"chargeLevel":85},
{"cost":640.76,"chargeLevel":66},
{"cost":975.62,"chargeLevel":98},
{"cost":946.42,"chargeLevel":1},
{"cost":760.94,"chargeLevel":94},
{"cost":282.86,"chargeLevel":63},
{"cost":55.21,"chargeLevel":8},
{"cost":545.49,"chargeLevel":94},
{"cost":580.85,"chargeLevel":77},
{"cost":782.25,"chargeLevel":45},
{"cost":849.61,"chargeLevel":90},
{"cost":16.31,"chargeLevel":90},
{"cost":716.97,"chargeLevel":96},
{"cost":12.68,"chargeLevel":4},
{"cost":490.15,"chargeLevel":12},
{"cost":499.5,"chargeLevel":26},
{"cost":366.35,"chargeLevel":95},
{"cost":272.62,"chargeLevel":54},
{"cost":607.57,"chargeLevel":30},
{"cost":470.85,"chargeLevel":19},
{"cost":840.53,"chargeLevel":2},
{"cost":769.29,"chargeLevel":26},
{"cost":168.25,"chargeLevel":91},
{"cost":355.13,"chargeLevel":36},
{"cost":812.13,"chargeLevel":65},
{"cost":19.04,"chargeLevel":43},
{"cost":903.3,"chargeLevel":5},
{"cost":332.7,"chargeLevel":21},
{"cost":624.83,"chargeLevel":9},
{"cost":437.89,"chargeLevel":36},
{"cost":781.89,"chargeLevel":79},
{"cost":329.77,"chargeLevel":12},
{"cost":882.48,"chargeLevel":42},
{"cost":646.95,"chargeLevel":79},
{"cost":995.5,"chargeLevel":51},
{"cost":477.05,"chargeLevel":3},
{"cost":6.93,"chargeLevel":78},
{"cost":929.05,"chargeLevel":75},
{"cost":519.16,"chargeLevel":75},
{"cost":82.53,"chargeLevel":8},
{"cost":993.82,"chargeLevel":49},
{"cost":533.24,"chargeLevel":16},
{"cost":487.73,"chargeLevel":23},
{"cost":12.85,"chargeLevel":99},
{"cost":628.49,"chargeLevel":91},
{"cost":886.39,"chargeLevel":52},
{"cost":553.58,"chargeLevel":72},
{"cost":205.31,"chargeLevel":44},
{"cost":679.9,"chargeLevel":2},
{"cost":651.59,"chargeLevel":7},
{"cost":274.59,"chargeLevel":4},
{"cost":490.29,"chargeLevel":84},
{"cost":757.74,"chargeLevel":97},
{"cost":992.66,"chargeLevel":99},
{"cost":781.11,"chargeLevel":80},
{"cost":690.36,"chargeLevel":14},
{"cost":583.98,"chargeLevel":28},
{"cost":172.83,"chargeLevel":62},
{"cost":694.39,"chargeLevel":52},
{"cost":326.61,"chargeLevel":75},
{"cost":213.37,"chargeLevel":6},
{"cost":687.29,"chargeLevel":56},
{"cost":526.52,"chargeLevel":10},
{"cost":642.43,"chargeLevel":98},
{"cost":78.98,"chargeLevel":23},
{"cost":821.8,"chargeLevel":60},
{"cost":663.01,"chargeLevel":80},
{"cost":689.34,"chargeLevel":45},
{"cost":813.47,"chargeLevel":92},
{"cost":393.81,"chargeLevel":25},
{"cost":701.66,"chargeLevel":7},
{"cost":153.61,"chargeLevel":62},
{"cost":718.37,"chargeLevel":27},
{"cost":672.67,"chargeLevel":36},
{"cost":192.67,"chargeLevel":62},
{"cost":148.89,"chargeLevel":59},
{"cost":301.36,"chargeLevel":12},
{"cost":927.47,"chargeLevel":82},
{"cost":168.39,"chargeLevel":65},
{"cost":819.51,"chargeLevel":32},
{"cost":896.58,"chargeLevel":50},
{"cost":805.34,"chargeLevel":98},
{"cost":526.82,"chargeLevel":68},
{"cost":416.71,"chargeLevel":98},
{"cost":295.64,"chargeLevel":9},
{"cost":967.94,"chargeLevel":16},
{"cost":695.61,"chargeLevel":66},
{"cost":880.19,"chargeLevel":78},
{"cost":783.68,"chargeLevel":87},
{"cost":968.87,"chargeLevel":6},
{"cost":138.89,"chargeLevel":38},
{"cost":390.62,"chargeLevel":15},
{"cost":940.5,"chargeLevel":84},
{"cost":551.7,"chargeLevel":88},
{"cost":34.21,"chargeLevel":42},
{"cost":340.26,"chargeLevel":69},
{"cost":93.32,"chargeLevel":24},
{"cost":375.71,"chargeLevel":29},
{"cost":9.25,"chargeLevel":40},
{"cost":961.19,"chargeLevel":31},
{"cost":343.29,"chargeLevel":71},
{"cost":757.53,"chargeLevel":85},
{"cost":156.59,"chargeLevel":68},
{"cost":253.17,"chargeLevel":80},
{"cost":377.4,"chargeLevel":78},
{"cost":929.46,"chargeLevel":54},
{"cost":538.68,"chargeLevel":18},
{"cost":676.09,"chargeLevel":97},
{"cost":118.65,"chargeLevel":70},
{"cost":435.43,"chargeLevel":68},
{"cost":168.36,"chargeLevel":7},
{"cost":65.33,"chargeLevel":88},
{"cost":314.78,"chargeLevel":31},
{"cost":12.21,"chargeLevel":76},
{"cost":616.94,"chargeLevel":23},
{"cost":717.18,"chargeLevel":99},
{"cost":815.71,"chargeLevel":65},
{"cost":573.47,"chargeLevel":3},
{"cost":861.78,"chargeLevel":36},
{"cost":774.89,"chargeLevel":83},
{"cost":828.71,"chargeLevel":17},
{"cost":426.48,"chargeLevel":62},
{"cost":860.33,"chargeLevel":38},
{"cost":801.09,"chargeLevel":22},
{"cost":983.57,"chargeLevel":29},
{"cost":808.48,"chargeLevel":83},
{"cost":99.12,"chargeLevel":96},
{"cost":749.1,"chargeLevel":1},
{"cost":90.74,"chargeLevel":45},
{"cost":360.56,"chargeLevel":87},
{"cost":292.71,"chargeLevel":24},
{"cost":572.79,"chargeLevel":10},
{"cost":25.52,"chargeLevel":88},
{"cost":204.61,"chargeLevel":16},
{"cost":213.35,"chargeLevel":12},
{"cost":5.99,"chargeLevel":88},
{"cost":996.14,"chargeLevel":70},
{"cost":173.29,"chargeLevel":36},
{"cost":127.02,"chargeLevel":44},
{"cost":633.37,"chargeLevel":17},
{"cost":507.62,"chargeLevel":86},
{"cost":839.54,"chargeLevel":34},
{"cost":317.04,"chargeLevel":68},
{"cost":919.73,"chargeLevel":83},
{"cost":844.15,"chargeLevel":67},
{"cost":383.62,"chargeLevel":49},
{"cost":326.08,"chargeLevel":4},
{"cost":853.37,"chargeLevel":68},
{"cost":903.46,"chargeLevel":91},
{"cost":993.05,"chargeLevel":40},
{"cost":699.27,"chargeLevel":72},
{"cost":234.52,"chargeLevel":21},
{"cost":187.14,"chargeLevel":14},
{"cost":705.45,"chargeLevel":31},
{"cost":860.57,"chargeLevel":81},
{"cost":105.18,"chargeLevel":3},
{"cost":143.5,"chargeLevel":94},
{"cost":681.61,"chargeLevel":73},
{"cost":686.21,"chargeLevel":10},
{"cost":654.4,"chargeLevel":66},
{"cost":146.05,"chargeLevel":64},
{"cost":943.89,"chargeLevel":38},
{"cost":249.09,"chargeLevel":79},
{"cost":273.0,"chargeLevel":76},
{"cost":812.67,"chargeLevel":64},
{"cost":865.91,"chargeLevel":73},
{"cost":118.24,"chargeLevel":24},
{"cost":384.48,"chargeLevel":5},
{"cost":564.25,"chargeLevel":38},
{"cost":300.43,"chargeLevel":9},
{"cost":192.01,"chargeLevel":85},
{"cost":618.57,"chargeLevel":10},
{"cost":278.14,"chargeLevel":96},
{"cost":290.63,"chargeLevel":13},
{"cost":60.63,"chargeLevel":2},
{"cost":578.46,"chargeLevel":37},
{"cost":515.96,"chargeLevel":42},
{"cost":217.7,"chargeLevel":59},
{"cost":930.85,"chargeLevel":11},
{"cost":90.51,"chargeLevel":16},
{"cost":267.36,"chargeLevel":5},
{"cost":1.22,"chargeLevel":41},
{"cost":907.16,"chargeLevel":38},
{"cost":783.38,"chargeLevel":7},
{"cost":11.65,"chargeLevel":89},
{"cost":738.59,"chargeLevel":55},
{"cost":1.92,"chargeLevel":54},
{"cost":888.44,"chargeLevel":81},
{"cost":705.63,"chargeLevel":100},
{"cost":651.18,"chargeLevel":27},
{"cost":632.1,"chargeLevel":22},
{"cost":202.58,"chargeLevel":69},
{"cost":94.95,"chargeLevel":28},
{"cost":627.92,"chargeLevel":10},
{"cost":113.95,"chargeLevel":41},
{"cost":818.01,"chargeLevel":4},
{"cost":79.44,"chargeLevel":18},
{"cost":351.92,"chargeLevel":97},
{"cost":769.85,"chargeLevel":86},
{"cost":561.32,"chargeLevel":63},
{"cost":649.7,"chargeLevel":23},
{"cost":316.92,"chargeLevel":24},
{"cost":465.02,"chargeLevel":39},
{"cost":257.53,"chargeLevel":55},
{"cost":123.07,"chargeLevel":24},
{"cost":573.78,"chargeLevel":17},
{"cost":615.85,"chargeLevel":73},
{"cost":364.15,"chargeLevel":46},
{"cost":586.54,"chargeLevel":86},
{"cost":7.15,"chargeLevel":13},
{"cost":531.04,"chargeLevel":56},
{"cost":352.01,"chargeLevel":91},
{"cost":35.9,"chargeLevel":59},
{"cost":878.45,"chargeLevel":21},
{"cost":940.81,"chargeLevel":21},
{"cost":294.21,"chargeLevel":56},
{"cost":660.56,"chargeLevel":51},
{"cost":374.21,"chargeLevel":26},
{"cost":354.52,"chargeLevel":53},
{"cost":190.0,"chargeLevel":16},
{"cost":767.98,"chargeLevel":2},
{"cost":278.0,"chargeLevel":95},
{"cost":259.6,"chargeLevel":67},
{"cost":53.8,"chargeLevel":35},
{"cost":120.14,"chargeLevel":24},
{"cost":668.28,"chargeLevel":86},
{"cost":896.37,"chargeLevel":5},
{"cost":765.86,"chargeLevel":93},
{"cost":619.03,"chargeLevel":9},
{"cost":460.56,"chargeLevel":23},
{"cost":953.26,"chargeLevel":12},
{"cost":126.89,"chargeLevel":80},
{"cost":931.61,"chargeLevel":77},
{"cost":837.09,"chargeLevel":81},
{"cost":862.9,"chargeLevel":13},
{"cost":792.59,"chargeLevel":46},
{"cost":717.16,"chargeLevel":42},
{"cost":188.47,"chargeLevel":2},
{"cost":443.61,"chargeLevel":47},
{"cost":594.29,"chargeLevel":40},
{"cost":56.75,"chargeLevel":13},
{"cost":716.81,"chargeLevel":37},
{"cost":486.74,"chargeLevel":93},
{"cost":296.13,"chargeLevel":72},
{"cost":108.64,"chargeLevel":99},
{"cost":151.67,"chargeLevel":45},
{"cost":122.96,"chargeLevel":6},
{"cost":641.18,"chargeLevel":44},
{"cost":366.25,"chargeLevel":52},
{"cost":609.1,"chargeLevel":69},
{"cost":703.94,"chargeLevel":23},
{"cost":823.69,"chargeLevel":8},
{"cost":741.38,"chargeLevel":53},
{"cost":34.03,"chargeLevel":100},
{"cost":26.9,"chargeLevel":4},
{"cost":434.02,"chargeLevel":83},
{"cost":198.23,"chargeLevel":94},
{"cost":603.21,"chargeLevel":81},
{"cost":319.96,"chargeLevel":92},
{"cost":260.02,"chargeLevel":65},
{"cost":833.12,"chargeLevel":31},
{"cost":167.18,"chargeLevel":8},
{"cost":509.5,"chargeLevel":15},
{"cost":446.51,"chargeLevel":10},
{"cost":948.26,"chargeLevel":40},
{"cost":523.0,"chargeLevel":100},
{"cost":363.85,"chargeLevel":89},
{"cost":547.49,"chargeLevel":27},
{"cost":55.99,"chargeLevel":23},
{"cost":252.95,"chargeLevel":33},
{"cost":74.96,"chargeLevel":85},
{"cost":979.58,"chargeLevel":50},
{"cost":796.49,"chargeLevel":16},
{"cost":190.99,"chargeLevel":71},
{"cost":175.84,"chargeLevel":63},
{"cost":475.51,"chargeLevel":57},
{"cost":797.28,"chargeLevel":4},
{"cost":820.63,"chargeLevel":5},
{"cost":227.48,"chargeLevel":73},
{"cost":377.24,"chargeLevel":46},
{"cost":797.88,"chargeLevel":25},
{"cost":643.26,"chargeLevel":23},
{"cost":358.32,"chargeLevel":84},
{"cost":876.95,"chargeLevel":50},
{"cost":318.33,"chargeLevel":72},
{"cost":724.13,"chargeLevel":66},
{"cost":956.75,"chargeLevel":5},
{"cost":756.49,"chargeLevel":89},
{"cost":665.97,"chargeLevel":73},
{"cost":697.77,"chargeLevel":46},
{"cost":14.07,"chargeLevel":100},
{"cost":606.53,"chargeLevel":38},
{"cost":674.36,"chargeLevel":28},
{"cost":146.3,"chargeLevel":36},
{"cost":239.17,"chargeLevel":26},
{"cost":24.27,"chargeLevel":5},
{"cost":262.69,"chargeLevel":96},
{"cost":614.72,"chargeLevel":15},
{"cost":769.91,"chargeLevel":99},
{"cost":618.54,"chargeLevel":13},
{"cost":425.71,"chargeLevel":18},
{"cost":570.06,"chargeLevel":97},
{"cost":386.69,"chargeLevel":53},
{"cost":457.02,"chargeLevel":49},
{"cost":487.86,"chargeLevel":7},
{"cost":299.39,"chargeLevel":59},
{"cost":49.83,"chargeLevel":57},
{"cost":222.42,"chargeLevel":84},
{"cost":733.07,"chargeLevel":79},
{"cost":294.92,"chargeLevel":67},
{"cost":182.76,"chargeLevel":73},
{"cost":173.4,"chargeLevel":9},
{"cost":411.86,"chargeLevel":73},
{"cost":576.52,"chargeLevel":36},
{"cost":423.11,"chargeLevel":47},
{"cost":650.19,"chargeLevel":18},
{"cost":425.49,"chargeLevel":100},
{"cost":583.19,"chargeLevel":96},
{"cost":35.43,"chargeLevel":59},
{"cost":449.93,"chargeLevel":29},
{"cost":534.13,"chargeLevel":73},
{"cost":579.96,"chargeLevel":59},
{"cost":801.63,"chargeLevel":87},
{"cost":37.7,"chargeLevel":39},
{"cost":450.81,"chargeLevel":54},
{"cost":599.5,"chargeLevel":98},
{"cost":745.29,"chargeLevel":48},
{"cost":511.63,"chargeLevel":2},
{"cost":346.49,"chargeLevel":47},
{"cost":571.46,"chargeLevel":62},
{"cost":184.04,"chargeLevel":70},
{"cost":227.68,"chargeLevel":44},
{"cost":432.4,"chargeLevel":46},
{"cost":966.73,"chargeLevel":79},
{"cost":809.67,"chargeLevel":81},
{"cost":251.83,"chargeLevel":6},
{"cost":530.11,"chargeLevel":21},
{"cost":574.45,"chargeLevel":50},
{"cost":300.04,"chargeLevel":1},
{"cost":406.8,"chargeLevel":44},
{"cost":413.55,"chargeLevel":34},
{"cost":490.38,"chargeLevel":22},
{"cost":84.03,"chargeLevel":27},
{"cost":357.39,"chargeLevel":99},
{"cost":633.0,"chargeLevel":99},
{"cost":899.37,"chargeLevel":23},
{"cost":929.66,"chargeLevel":67},
{"cost":883.94,"chargeLevel":76},
{"cost":81.54,"chargeLevel":49},
{"cost":174.82,"chargeLevel":28},
{"cost":708.63,"chargeLevel":94},
{"cost":223.88,"chargeLevel":68},
{"cost":380.64,"chargeLevel":43},
{"cost":721.21,"chargeLevel":30},
{"cost":597.24,"chargeLevel":87},
{"cost":860.21,"chargeLevel":7},
{"cost":388.58,"chargeLevel":46},
{"cost":324.9,"chargeLevel":47},
{"cost":693.54,"chargeLevel":58},
{"cost":173.52,"chargeLevel":22},
{"cost":665.36,"chargeLevel":78},
{"cost":101.37,"chargeLevel":76},
{"cost":86.11,"chargeLevel":81},
{"cost":491.79,"chargeLevel":92},
{"cost":245.63,"chargeLevel":47},
{"cost":35.87,"chargeLevel":6},
{"cost":203.08,"chargeLevel":72},
{"cost":641.59,"chargeLevel":48},
{"cost":40.62,"chargeLevel":7},
{"cost":747.63,"chargeLevel":79},
{"cost":817.05,"chargeLevel":90},
{"cost":569.11,"chargeLevel":41},
{"cost":693.82,"chargeLevel":43},
{"cost":190.54,"chargeLevel":27},
{"cost":29.14,"chargeLevel":15},
{"cost":191.67,"chargeLevel":95},
{"cost":726.16,"chargeLevel":34},
{"cost":517.97,"chargeLevel":96},
{"cost":254.04,"chargeLevel":56},
{"cost":489.41,"chargeLevel":34},
{"cost":621.92,"chargeLevel":90},
{"cost":475.39,"chargeLevel":14},
{"cost":381.2,"chargeLevel":9},
{"cost":637.49,"chargeLevel":7},
{"cost":784.57,"chargeLevel":60},
{"cost":200.2,"chargeLevel":40},
{"cost":99.09,"chargeLevel":66},
{"cost":733.01,"chargeLevel":40},
{"cost":972.88,"chargeLevel":96},
{"cost":203.83,"chargeLevel":16},
{"cost":345.84,"chargeLevel":93},
{"cost":911.53,"chargeLevel":31},
{"cost":480.55,"chargeLevel":73},
{"cost":761.44,"chargeLevel":23},
{"cost":702.16,"chargeLevel":86},
{"cost":909.12,"chargeLevel":30},
{"cost":470.65,"chargeLevel":28},
{"cost":100.31,"chargeLevel":51},
{"cost":932.22,"chargeLevel":99},
{"cost":473.13,"chargeLevel":80},
{"cost":540.13,"chargeLevel":36},
{"cost":147.38,"chargeLevel":85},
{"cost":888.39,"chargeLevel":16},
{"cost":195.42,"chargeLevel":20},
{"cost":358.33,"chargeLevel":79}]